Workbook
Name base_calculo: 'DADOS DO CONTRIBUINTE'!#REF!
Name base_calculo: DESPESAS!#REF!
Name base_calculo: 'RELATÓRIO FINAL'!#REF!
Name base_calculo: RENDIMENTOS!#REF!
Name base_calculo: RESUMO!$C$11
Name despesas_dedutiveis: DESPESAS!$C$7
Name rendimentos: RENDIMENTOS!$C$7
Name trabalho: #REF!

Sheet DADOS DO CONTRIBUINTE
C3: INFORMAÇÕES PESSOAIS
C4: Preencha os dados cadastrais
C6: NOME COMPLETO | D6: Sabrina Rodrigues
C7: CPF | D7: 10298745633
C8: DATA DE NASCIMENTO | D8: 36141
C9: ESTADO CIVIL | D9: Solteira
C10: PROFISSÃO | D10: Analista de sistema
C11: TELEFONE | D11: 2126032865
C12: CELULAR | D12: 21975566462
C13: E-MAIL | D13: sabrina.idev@outlook.com
C15: ENDEREÇO
C17: CEP | D17: 55442702
C18: LOGRADOURO | D18: Rua Ameixa roxa
C19: NÚMERO | D19: 36
C20: BAIRRO | D20: Sol Poente
C21: CIDADE | D21: Rio de Janeiro
C22: ESTADO | D22: Rio de Janeiro
C24: DEPENDENTES (OPCIONAL)
C26: HOUVE ALTERAÇÕES DA ENTREGA ANTERIOR | D26: NÃO
C27: RESIDENTE NO EXTERIOR | D27: NÃO
C28: DEPENDENTE / CÔNJUGE | D28: NÃO
C29: NOME DO DEPENDENTE
C30: CPF DO DEPENDENTE
C31: DATA DE NASCIMENTO

Sheet RENDIMENTOS
C3: RENDIMENTOS BANCÁRIOS
C4: Preencha os dados de tudo que recebeu no ano
C6: TOTAL
C7: =SUM(D12*D13,D14,D15,D20*D21,D22*D23,D24*D25,D26*D27,D28*D29,D34,D35,D36) -> 49918.333
C10: TRABALHO
C11: BANCO | D11: 119 - Banco Western Union do Brasil
C12: SALÁRIO | D12: 3250
C13: MESES TRABALHADOS | D13: 12
C14: FÉRIAS | D14: =D12/3 -> 1083.3333
C15: PARTICIPAÇÃO DOS LUCROS (PLR) | D15: 2500
C16: ANEXO🖇️ | D16: bancox.pdf
D17: =SUM(D12*D13,D14,D15) -> 42583.333
C19: OUTRAS RENDAS
C20: ALUGUEL RECEBIDO | D20: 1200
C21: MESES DE ALUGUEL | D21: 5
C22: APOSENTADORIA | D22: 0
C23: TEMPO DE APOSENTADORIA | D23: 0
C24: PRÓ LABORE | D24: 0
C25: TEMPO DE PRÓ LABORE | D25: 0
C26: PENSÃO RECEBIDA | D26: 0
C27: TEMPO DE PENSÃO | D27: 0
C28: RENDIMENTOS AUTÔNOMO | D28: 0
C29: TEMPO DE RENDIMENTO | D29: 0
C30: ANEXO🖇️ | D30: bancox.pdf
D31: =SUM(D20*D21,D22*D23,D24*D25,D26*D27,D28*D29) -> 6000
C33: APLICAÇÃO FINANCEIRA
C34: INVESTIMENTOS | D34: 1335
C35: DIVIDENDOS | D35: 0
C36: JUROS | D36: 0
C37: ANEXO🖇️ | D37: bancoz.pdf
D38: =SUM(D34,D35,D36) -> 1335

Sheet DESPESAS
C3: DESPESAS DEDUTÍVEIS
C4: Preencha os dados com os descontos no ano
C6: TOTAL
C7: =SUM(D11*D12,D13,D14,D15,D20*D21,D22*D23,D24*D25,D30,D32,D34,D40*D41,D46*D47) -> 20987.05
C10: SAÚDE
C11: PLANO DE SAÚDE | D11: 350
C12: MESES DE PLANO DE SAÚDE | D12: 6
C13: CONSULTAS MÉDICAS | D13: 500
C14: DENTISTAS | D14: 1200
C15: EXAMES | D15: 2700
C16: ANEXO🖇️ | D16: saude.pdf
D17: =SUM(D11*D12,D13,D14,D15) -> 6500
C19: EDUCAÇÃO
C20: ESCOLA | D20: 1200
C21: MESES DE ANO LETIVO | D21: 12
C22: FACULDADE | D22: 0
C23: MESES DE GRADUAÇÃO | D23: 0
C24: PÓS GRADUAÇÃO | D24: 0
C25: MESES DE PÓS-GRADUAÇÃO | D25: 0
C26: ANEXO🖇️ | D26: educacao.pdf
D27: =SUM(D20*D21,D22*D23,D24*D25) -> 14400
C29: PREVIDÊNCIA
C30: INSS | D30: 0
C31: TEMPO DE CONTRIBUIÇÃO DO INSS | D31: 0
C32: PREVIDÊNCIA PRIVADA | D32: 0
C33: TEMPO DE CONTRIBUIÇÃO PRIVADA | D33: 0
C34: SIMPLES NACIONAL | D34: 87.05
C35: TEMPO SIMPLES NACIONAL | D35: 10
C36: ANEXO🖇️ | D36: previdencia.pdf
D37: =SUM(D30*D31,D32*D33,D34*D35) -> 870.5
C39: DEPENDENTES
C40: VALOR POR DEPENDENTES | D40: 0
C41: QUANTIDADES DE DEPENDENTES | D41: 0
C42: ANEXO🖇️
D43: =SUM(D40*D41) -> 0
C45: PENSÃO ALIMENTÍCIA
C46: VALOR PAGO | D46: 0
C47: TEMPO DE CONTRIBUIÇÃO PENSÃO | D47: 0
C48: ANEXO🖇️
D49: =SUM(D46*D47) -> 0

Sheet RESUMO
C3: RESUMO DO IR
C4: São todos os valores de entrada mês a mês de receita
C7: 📠BASE DOS CÁCULOS
C9: RENDIMENTOS | D9: =rendimentos -> 49918.333
C10: DESPESAS | D10: =despesas_dedutiveis -> 20987.05
C11: =D9-D10 -> 28931.283
C14: 📊 IMPOSTO ESTIMADO
D16: =base_calculo*15% -> 4339.6925
C19: 🧐IR RETIDO DA FONTE
C21: RETIDO DA FONTE | D21: =rendimentos*12% -> 5990.2
C22: =ABS(D21-D16) -> 1650.5075
D25: =IF(D21>D16,"✅ RESTITUIÇÃO","⚠️ IMPOSTO A PAGAR") -> ✅ RESTITUIÇÃO

Sheet RELATÓRIO FINAL
C3: RELATÓRIO FINAL
C4: São todos os valores em um relatório executivo
C8: DADOS DO CONTRIBUINTE
C10: NOME COMPLETO | D10: Sabrina Rodrigues
C11: CPF | D11: 10298745633
C14: RENDIMENTOS
C16: TRABALHO | D16: =RENDIMENTOS!D17 -> 42583.333
C17: OUTRAS RENDAS | D17: =RENDIMENTOS!D31 -> 6000
C18: INVESTIMENTOS | D18: =RENDIMENTOS!D38 -> 1335
C21: DEDUÇÕES
C23: SAÚDE | D23: =DESPESAS!D17 -> 6500
C24: EDUCAÇÃO | D24: =DESPESAS!D27 -> 14400
C25: PREVIDÊNCIA | D25: =DESPESAS!D37 -> 870.5
C26: DEPENDENTES | D26: =DESPESAS!D43 -> 0
C27: PENSÃO ALIMENTÍCIA | D27: =DESPESAS!D48 -> 0
C30: BASE DE CÁCULO | D30: =[0]!base_calculo -> 28931.283
C31: IMPOSTO ESTIMADO | D31: =RESUMO!D16 -> 4339.6925
C32: RETIDO DA FONTE | D32: =RESUMO!D21 -> 5990.2

Sheet BANCOS
A1: BANCOS
A2: 1 - Banco do Brasil
A3: 102 - XP Investimentos CCTVM S.A.
A4: 104 - Caixa Econômica Federal
A5: 119 - Banco Western Union do Brasil
A6: 184 - Banco Itaú BBA S.A.
A7: 197 - Stone Pagamentos
A8: 208 - Banco BTG Pactual
A9: 212 - Banco Original
A10: 218 - Banco Bonsucesso
A11: 229 - Banco Cruzeiro do Sul
A12: 237 - Banco Bradesco
... A51: 82 - Banco Topázio
